topsis/TopsisPackage_102216017.py
topsis/__init__.py
TopsisPackage_102216017-1.0.0.dist-info/LICENSE
TopsisPackage_102216017-1.0.0.dist-info/METADATA
TopsisPackage_102216017-1.0.0.dist-info/WHEEL
TopsisPackage_102216017-1.0.0.dist-info/entry_points.txt
TopsisPackage_102216017-1.0.0.dist-info/top_level.txt
TopsisPackage_102216017-1.0.0.dist-info/RECORD
