Metadata-Version: 2.2
Name: TopsisPackage_102216017
Version: 1.0.0
Summary: A Python implementation of the TOPSIS decision-making method.
Home-page: https://github.com/Sumita15/topsis
Author: Sumita
Author-email: ssumita_be22@thapar.edu
License: MIT
Classifier: Programming Language :: Python :: 3
Classifier: License :: OSI Approved :: MIT License
Classifier: Operating System :: OS Independent
Requires-Python: >=3.6
License-File: LICENSE
